[{
    "id": 1,
    "name": "Omar Demsey",
    "email": "odemsey0@oracle.com",
    "gender": "Genderqueer",
    "phone": "166-886-9589",
    "salary": 422246,
    "image": "https://randomuser.me/api/portraits/men/43.jpg"
  }, {
    "id": 2,
    "name": "Haleigh Skoyles",
    "email": "hskoyles1@merriam-webster.com",
    "gender": "Genderfluid",
    "phone": "267-227-3488",
    "salary": 32246,
    "image": "https://randomuser.me/api/portraits/women/43.jpg"
  }, {
    "id": 3,
    "name": "Bond McColgan",
    "email": "bmccolgan2@harvard.edu",
    "gender": "Non-binary",
    "phone": "684-492-7028",
    "salary": 57823,
    "image": "https://randomuser.me/api/portraits/men/44.jpg"
  }, {
    "id": 4,
    "name": "Wang Lamdin",
    "email": "wlamdin3@wisc.edu",
    "gender": "Polygender",
    "phone": "902-767-5710",
    "salary": 25000,
    "image": "https://randomuser.me/api/portraits/men/45.jpg"
  }, {
    "id": 5,
    "name": "Nadia Farenden",
    "email": "nfarenden4@list-manage.com",
    "gender": "Male",
    "phone": "583-749-3426",
    "salary": 29452,
    "image": "https://randomuser.me/api/portraits/women/44.jpg"
  }, {
    "id": 6,
    "name": "Lillis Jonke",
    "email": "ljonke5@youtu.be",
    "gender": "Genderqueer",
    "phone": "417-969-6498",
    "salary": 42581,
    "image": "https://randomuser.me/api/portraits/men/46.jpg"
  }, {
    "id": 7,
    "name": "Aprilette Winsborrow",
    "email": "awinsborrow6@admin.ch",
    "gender": "Genderqueer",
    "phone": "142-176-0620",
    "salary": 39896,
    "image": "https://randomuser.me/api/portraits/men/47.jpg"
  }, {
    "id": 8,
    "name": "Marice Daly",
    "email": "mdaly7@flickr.com",
    "gender": "Genderqueer",
    "phone": "122-767-6568",
    "salary": 24201,
    "image": "https://randomuser.me/api/portraits/women/41.jpg"
  }, {
    "id": 9,
    "name": "Tonie Van den Hof",
    "email": "tvan8@bluehost.com",
    "gender": "Genderfluid",
    "phone": "527-207-7890",
    "salary": 28000,
    "image": "https://randomuser.me/api/portraits/women/47.jpg"
  }, {
    "id": 10,
    "name": "Gretel Liccardo",
    "email": "gliccardo9@multiply.com",
    "gender": "Genderfluid",
    "phone": "756-252-3603",
    "salary": 40152,
    "image": "https://randomuser.me/api/portraits/men/49.jpg"
  }, {
    "id": 11,
    "name": "Olvan Blunderfield",
    "email": "oblunderfielda@sina.com.cn",
    "gender": "Genderqueer",
    "phone": "767-734-0469",
    "salary": 53000,
    "image": "https://randomuser.me/api/portraits/women/45.jpg"
  }, {
    "id": 12,
    "name": "Tim Wildish",
    "email": "twildishb@woothemes.com",
    "gender": "Bigender",
    "phone": "916-937-4423",
    "salary": 52246,
    "image": "https://randomuser.me/api/portraits/men/52.jpg"
  }, {
    "id": 13,
    "name": "Lamont Durrans",
    "email": "ldurransc@miitbeian.gov.cn",
    "gender": "Non-binary",
    "phone": "278-221-9138",
    "salary": 52246,
    "image": "https://randomuser.me/api/portraits/women/52.jpg"
  }, {
    "id": 14,
    "name": "Adel McNabb",
    "email": "amcnabbd@spotify.com",
    "gender": "Polygender",
    "phone": "818-702-1403",
    "salary": 58214,
    "image": "https://randomuser.me/api/portraits/men/53.jpg"
  }, {
    "id": 15,
    "name": "Ami Pace",
    "email": "apacee@earthlink.net",
    "gender": "Genderfluid",
    "phone": "365-362-0605",
    "salary": 18000,
    "image": "https://randomuser.me/api/portraits/women/53.jpg"
  }]